Workbook

Sheet 00_Data_Notes
A1: Random Blind-Box Full-Set Collection Strategy | Data Collection
A4: Field Type | B4: Color | C4: Meaning | E4: Collection Steps | F4: Main Worksheet | G4: Completion Flag
A5: Required | C5: Data essential for modeling | E5: 1. Select series and verify rules | F5: 01_Series_Basic_Info | G5: Confirm independent random draws, version, and character scope
A6: Conditionally Required | C6: Must fill in when the condition is met | E6: 2. Organize characters and probabilities | F6: 02_Character_Probabilities | G6: Probability sum passes check
A7: Optional | C7: Helps improve report quality but not a minimum requirement | E7: 3. Collect secondary-market prices and evidence | F7: 03_Secondary_Market_Raw_Data | G7: Each character reaches recommended sample size
A8: Auto-calculated | C8: Generated automatically by formula | E8: 4. Supplement transaction rules and self-check | F8: 04—06Worksheet | G8: Quality checklist has no major gaps
A10: Progress Metric | B10: Current Value | C10: Target | E10: Submission Checklist | F10: Completed?
A11: Number of target characters filled | B11: =COUNTIFS('02_Character_Probabilities'!B3:B10,"<>",'02_Character_Probabilities'!C3:C10,"Yes") -> 8 | C11: 6–12 | E11: Excel workbook fully completed | F11: Completed
A12: Number of secondary-market raw records | B12: =COUNTIF('03_Secondary_Market_Raw_Data'!A3:A299,"<>") -> 134 | C12: Preferably ≥15 per character | E12: Official info screenshots and links saved | F12: Completed
A13: Number of valid records included in analysis | B13: =COUNTIF('03_Secondary_Market_Raw_Data'!T3:T299,"Yes") -> 127 | C13: At least 8 per character is more reliable | E13: Secondary-market screenshots named by evidence ID | F13: Completed
A14: Valid records missing evidence ID | B14: =COUNTIFS('03_Secondary_Market_Raw_Data'!T3:T299,"Yes",'03_Secondary_Market_Raw_Data'!V3:V299,"") -> 0 | C14: 0 records | E14: Excluded data retained with reasons stated | F14: Completed
A15: Completed quality-check items | B15: =COUNTIF('06_Data_Quality_Check'!C3:C30,"Pass") -> 28 | C15: All required check items | E15: Folder named and packaged as required | F15: Completed

Sheet 01_Series_Basic_Info
A1: Series Basic Information and Official Rules
A2: Field Type | B2: Field Name | C2: Entry
A3: Required | B3: Full Series Name | C3: DEATH NOTE -My Dear Light- POP UP SHOP (Misa-themed exclusive pop-up / PARCO offline matte badge)
A4: Required | B4: Work / Title Name | C4: DEATH NOTE (デスノート / Death Note)
A5: Required | B5: Product Type | C5: Blind-box metal badge (トレーディング缶バッジ / Trading Badge)
A6: Required | B6: Product Specs / Size | C6: Diameter Φ56mm per badge; single independent blind bag; BOX contains 8 packs (8 badges)
A7: Required | B7: Release Batch / Version | C7: Batch1 Nagoya PARCO (2025.2.7–2.24); Batch2 Ikebukuro PARCO (2025.3.19–3.30); Batch3 Fukuoka PARCO (2025.5.23–6.8); Post restock (reservation 2026.4.3–5.10, ship June)
A8: Optional | B8: Official Release Date | C8: 2025-02-07
A9: Required | B9: Total Number of Target Characters n | C9: 8
A10: Required | B10: Official Random Unit Price | C10: 550 JPY (tax incl., single); BOX 4,400 JPY (tax incl.); China retail about 39.8 CNY
A11: Required | B11: Official Purchase Channels | C11: Offline: Nagoya/Ikebukuro/Fukuoka PARCO pop-up venues; Online restock: Sofmap ONLINE, PARCO ART official reservation
A12: Required | B12: Official Shipping Rules | C12: No shipping at offline venues; online restock shipping not clearly stated in public materials (subject to actual checkout)
A13: Optional | B13: Other Official Fees | C13: 0
A14: Required | B14: Items per Pack | C14: 1
A15: Required | B15: Independent Random per Pack? | C15: Yes
A16: Required | B16: Public Pity / Guarantee Mechanism? | C16: No pity for single packs (1 full BOX of 8 guarantees all 8 standard designs, no duplicates)
A17: Required | B17: Box Has No Duplicates / Fixed Box Ratio? | C17: Yes. Full box fixed set of 8 designs with no duplicates
A18: Required | B18: Hidden / Secret Designs? | C18: No. No hidden/SP/variant/foil designs; only 8 fixed original illustrations
A19: Conditionally Required | B19: Handling of Hidden Designs | C19: N/A (no hidden designs)
A20: Required | B20: Official Character Probabilities Published? | C20: Yes
A21: Conditionally Required | B21: Official Probability Description | C21: No rarity tiers; 8 designs equal factory ratio; BOX mechanism guarantees full set of 8
A22: Required | B22: Official Information Source URL | C22: 1.https://art.parco.jp/parcofactory/detail/?id=1701 2.https://prtimes.jp/main/html/rd/p/000003340.000003639.html 3.https://www.sofmap.com/product_detail_sp.aspx?sku=101920630 4.https://ikebukuro.parco.jp/
A23: Required | B23: Official Information Collection Date | C23: 1.PARCO ART:2025-01-22 (first)/2025-03-20 (recheck); 2.PR TIMES:2025-01-22; 3.Sofmap:2026-04-03/2026-04-15; 4.Ikebukuro PARCO:2025-03-18
A24: Required | B24: Official Evidence ID | C24: Sofmap SKU:101920630; PARCO FACTORY EVENT No.1701; Manufacturer: 株式会社アヴェンジャーズ
A25: Optional | B25: Reason for Choosing This Series | C25: Fixed 8 designs, no hidden; BOX guarantees full set no duplicates; independent random packs; complete official info; suitable for base blind-draw modeling and data collection
A26: Optional | B26: Other Remarks | C26: Finish: matte print, proportional single-character art, no glitter/relief. Purchase limit: max 1 BOX per person per checkout. Full set of 8: 1.Light Yagami front view 2.Light Yagami profile 3.L light-gray portrait 4.L dark-gray profile 5.Misa Amane smiling 6.Misa Amane choker 7.Near 8.Mello. All official pages archived via WebArchive.

Sheet 02_Character_Probabilities
A1: Character List and Draw Probabilities
A2: Character ID | B2: Character Name | C2: Target Character? | D2: Character Version / Design | E2: Official Probability | F2: Baseline Probability p_i | G2: Probability Setting Method | H2: Probability Source URL | I2: Low-Probability Scenario | J2: High-Probability Scenario | K2: Remarks | M2: Probability Check | N2: Result
A3: 1 | B3: Light Yagami, front view | C3: Yes | D3: front view | E3: Not published | F3: 0.125 | G3: Equal probability | H3: https://art.parco.jp/parcofactory/detail/?id=1701 | K3: Standard design | M3: Number of Target Characters | N3: =COUNTIF(C3:C10,"Yes") -> 8
A4: 2 | B4: Light Yagami, profile | C4: Yes | D4: profile | E4: Not published | F4: 0.125 | G4: Equal probability | H4: https://art.parco.jp/parcofactory/detail/?id=1701 | K4: Standard design | M4: Sum of Baseline Probabilities | N4: =SUM(F3:F10) -> 1
A5: 3 | B5: L, light-gray portrait | C5: Yes | D5: light-gray portrait | E5: Not published | F5: 0.125 | G5: Equal probability | H5: https://art.parco.jp/parcofactory/detail/?id=1701 | K5: Standard design | M5: Equals 1? | N5: =IF(ABS(N4-1)<0.0001,"Pass","Needs check") -> Pass
A6: 4 | B6: L, dark-gray profile | C6: Yes | D6: dark-gray profile | E6: Not published | F6: 0.125 | G6: Equal probability | H6: https://art.parco.jp/parcofactory/detail/?id=1701 | K6: Standard design | M6: Number of Missing Baseline Probabilities | N6: =COUNTIFS(C3:C10,"Yes",F3:F10,"") -> 0
A7: 5 | B7: Misa Amane, smiling | C7: Yes | D7: smiling | E7: Not published | F7: 0.125 | G7: Equal probability | H7: https://art.parco.jp/parcofactory/detail/?id=1701 | K7: Standard design
A8: 6 | B8: Misa Amane, choker | C8: Yes | D8: choker | E8: Not published | F8: 0.125 | G8: Equal probability | H8: https://art.parco.jp/parcofactory/detail/?id=1701 | K8: Standard design
A9: 7 | B9: Near | C9: Yes | D9: looking down, white paper | E9: Not published | F9: 0.125 | G9: Equal probability | H9: https://art.parco.jp/parcofactory/detail/?id=1701 | K9: Standard design
A10: 8 | B10: Mello | C10: Yes | D10: red-brown coat | E10: Not published | F10: 0.125 | G10: Equal probability | H10: https://art.parco.jp/parcofactory/detail/?id=1701 | K10: Standard design

Sheet 03_Secondary_Market_Raw_Data
A1: Secondary-Market Raw Records (one row per listing)
A2: Record ID | B2: Character Name | C2: Platform | D2: Product Title | E2: Product Link | F2: Collection Date | G2: Listing Price | H2: Free Shipping? | I2: Buyer Shipping Cost | J2: Platform Fees | K2: Actual Landed Cost | L2: Quantity | M2: Unit Converted Price | N2: Product Version | O2: Product Specs | P2: Condition | Q2: Sold as Single Character? | R2: Bundled? | S2: Abnormal Price? | T2: Include in Analysis? | U2: Exclusion Reason | V2: Evidence ID | W2: Screenshot File Name | X2: Remarks
A3: 1 | B3: Light Yagami, front view | C3: Xianyu | D3: 【【包邮出】死亡笔记 名古屋快闪 夜神月正脸徽章】 | E3: https://m.tb.cn/h.8hZ5v4h | F3: 46239 | G3: 45 | H3: Yes | I3: 0 | J3: 0 | K3: =IF(OR(G3="",G3=0),"",G3+IF(I3="",0,I3)+IF(J3="",0,J3)) -> 45 | L3: 1 | M3: =IF(OR(K3="",L3=0),"",K3/L3) -> 45 | N3: My Dear Light | O3: Φ56mm matte | P3: Opened, good condition | Q3: Yes | R3: No | S3: No | T3: Yes | V3: MKT-001 | W3: MKT-001.png
A4: 2 | B4: Light Yagami, front view | C4: Xianyu | D4: 【包邮出】死亡笔记名古屋快闪夜神月正脸】 | E4: https://m.tb.cn/h.8hZ6c8g | F4: 46239 | G4: 70 | H4: Yes | I4: 0 | J4: 0 | K4: =IF(OR(G4="",G4=0),"",G4+IF(I4="",0,I4)+IF(J4="",0,J4)) -> 70 | L4: 1 | M4: =IF(OR(K4="",L4=0),"",K4/L4) -> 70 | N4: My Dear Light | O4: Φ56mm matte | P4: Opened, good condition | Q4: Yes | R4: No | S4: No | T4: Yes | V4: MKT-002 | W4: MKT-002.png
A5: 3 | B5: Light Yagami, front view | C5: Xianyu | D5: 【出】死亡笔记 名古屋快闪吧唧 夜神月正脸】 | E5: https://m.tb.cn/h.85loirB | F5: 46239 | G5: 60 | H5: Yes | J5: 0 | K5: =IF(OR(G5="",G5=0),"",G5+IF(I5="",0,I5)+IF(J5="",0,J5)) -> 60 | L5: 1 | M5: =IF(OR(K5="",L5=0),"",K5/L5) -> 60 | N5: My Dear Light | O5: Φ56mm matte | P5: Sealed, new | Q5: Yes | R5: No | S5: No | T5: Yes | V5: MKT-003 | W5: MKT-003.png
A6: 4 | B6: Light Yagami, front view | C6: Xianyu | D6: 【标价非偏 不要直拍 先tt我 死亡笔记夜神月名古屋正脸吧唧】 | E6: https://m.tb.cn/h.8TobHp2 | F6: 46239 | G6: 44 | H6: Yes (excl. remote areas | J6: 0 | K6: =IF(OR(G6="",G6=0),"",G6+IF(I6="",0,I6)+IF(J6="",0,J6)) -> 44 | L6: 1 | M6: =IF(OR(K6="",L6=0),"",K6/L6) -> 44 | N6: My Dear Light | O6: Φ56mm matte | P6: Slight defect | Q6: Yes | R6: No | S6: No | T6: Yes | V6: MKT-004 | W6: MKT-004.png
A7: 5 | B7: Light Yagami, profile | C7: Xianyu | D7: 【夜神月侧脸吧唧 有原袋 保存良好】 | E7: https://m.tb.cn/h.85lSeVr | F7: 46239 | G7: 70 | H7: No | I7: 10 | J7: 0 | K7: =IF(OR(G7="",G7=0),"",G7+IF(I7="",0,I7)+IF(J7="",0,J7)) -> 80 | L7: 1 | M7: =IF(OR(K7="",L7=0),"",K7/L7) -> 80 | N7: My Dear Light | O7: Φ56mm matte | P7: Sealed, new | Q7: Yes | R7: No | S7: No | T7: Yes | V7: MKT-005 | W7: MKT-005.png
A8: 6 | B8: Light Yagami, profile | C8: Xianyu | D8: 【【出】死亡笔记DeathNote名古屋池袋快闪吧唧，夜神月侧】 | E8: https://m.tb.cn/h.85lSVae | F8: 46239 | G8: 68 | H8: No | I8: 12 | J8: 0 | K8: =IF(OR(G8="",G8=0),"",G8+IF(I8="",0,I8)+IF(J8="",0,J8)) -> 80 | L8: 1 | M8: =IF(OR(K8="",L8=0),"",K8/L8) -> 80 | N8: My Dear Light | O8: Φ56mm matte | P8: Sealed, new | Q8: Yes | R8: No | S8: No | T8: Yes | V8: MKT-006 | W8: MKT-006.png
A9: 7 | B9: Light Yagami, front view | C9: Xianyu | D9: 【出夜神月名古屋吧唧】【死亡笔记】 | E9: https://m.tb.cn/h.85ldtv8 | F9: 46239 | G9: 45.9 | H9: No | I9: 12 | J9: 0 | K9: =IF(OR(G9="",G9=0),"",G9+IF(I9="",0,I9)+IF(J9="",0,J9)) -> 57.9 | L9: 1 | M9: =IF(OR(K9="",L9=0),"",K9/L9) -> 57.9 | N9: My Dear Light | O9: Φ56mm matte | P9: Opened, good condition | Q9: Yes | R9: No | S9: No | T9: Yes | V9: MKT-007 | W9: MKT-007.png
A10: 8 | B10: Light Yagami, profile | C10: Xianyu | D10: 【【出】死亡笔记 My Dear Light快闪吧唧 夜神月】 | E10: https://m.tb.cn/h.8TMIVgE | F10: 46239 | G10: 58 | H10: Yes (excl. remote areas | I10: 0 | J10: 0 | K10: =IF(OR(G10="",G10=0),"",G10+IF(I10="",0,I10)+IF(J10="",0,J10)) -> 58 | L10: 1 | M10: =IF(OR(K10="",L10=0),"",K10/L10) -> 58 | N10: My Dear Light | O10: Φ56mm matte | P10: Condition unclear | Q10: Yes | R10: No | S10: No | T10: Yes | V10: MKT-008 | W10: MKT-008.png
A11: 9 | B11: Light Yagami, profile | C11: Xianyu | D11: 【【出】死亡笔记 My Dear Light快闪吧唧 夜神月】 | E11: https://m.tb.cn/h.8gPsqAk | F11: 46239 | G11: 67 | H11: No | I11: 12 | J11: 0 | K11: =IF(OR(G11="",G11=0),"",G11+IF(I11="",0,I11)+IF(J11="",0,J11)) -> 79 | L11: 1 | M11: =IF(OR(K11="",L11=0),"",K11/L11) -> 79 | N11: My Dear Light | O11: Φ56mm matte | P11: Slight defect | Q11: Yes | R11: No | S11: No | T11: Yes | V11: MKT-009 | W11: MKT-009.png
A12: 10 | B12: Light Yagami, profile | C12: Xianyu | D12: 【出国现】死亡笔记 名古屋快闪原画吧唧 夜神月 包邮】 | E12: https://m.tb.cn/h.8hZZTQq | F12: 46241 | G12: 50 | H12: Yes | I12: 0 | J12: 0 | K12: =IF(OR(G12="",G12=0),"",G12+IF(I12="",0,I12)+IF(J12="",0,J12)) -> 50 | L12: 1 | M12: =IF(OR(K12="",L12=0),"",K12/L12) -> 50 | N12: My Dear Light | O12: Φ56mm matte | P12: Opened, good condition | Q12: Yes | R12: No | S12: No | T12: Yes | V12: MKT-010 | W12: MKT-010.png
A13: 11 | B13: Light Yagami, profile | C13: Xianyu | D13: 【死亡笔记 名古屋快闪吧唧 夜神月】 | E13: https://m.tb.cn/h.8hZ0bn4 | F13: 46241 | G13: 56 | H13: Yes | I13: 0 | J13: 0 | K13: =IF(OR(G13="",G13=0),"",G13+IF(I13="",0,I13)+IF(J13="",0,J13)) -> 56 | L13: 1 | M13: =IF(OR(K13="",L13=0),"",K13/L13) -> 56 | N13: My Dear Light | O13: Φ56mm matte | P13: Opened, good condition | Q13: Yes | R13: No | S13: No | T13: Yes | V13: MKT-011 | W13: MKT-011.png
A14: 12 | B14: Light Yagami, front view | C14: Xianyu | D14: 【一位老员工。。直出50，不包邮】 | E14: https://m.tb.cn/h.8hZTPEH | F14: 46241 | G14: 50 | H14: No | I14: 10 | J14: 0 | K14: =IF(OR(G14="",G14=0),"",G14+IF(I14="",0,I14)+IF(J14="",0,J14)) -> 60 | L14: 1 | M14: =IF(OR(K14="",L14=0),"",K14/L14) -> 60 | N14: My Dear Light | O14: Φ56mm matte | P14: Slight defect | Q14: Yes | R14: No | S14: No | T14: Yes | V14: MKT-012 | W14: MKT-012.png
A15: 13 | B15: Light Yagami, front view | C15: Xianyu | D15: 【出夜神月名古屋吧唧 48包非偏】 | E15: https://m.tb.cn/h.8Toancr | F15: 46241 | G15: 48.29 | H15: Yes | I15: 0 | J15: 0 | K15: =IF(OR(G15="",G15=0),"",G15+IF(I15="",0,I15)+IF(J15="",0,J15)) -> 48.29 | L15: 1 | M15: =IF(OR(K15="",L15=0),"",K15/L15) -> 48.29 | N15: My Dear Light | O15: Φ56mm matte | P15: Condition not specified | Q15: Yes | R15: No | S15: No | T15: Yes | V15: MKT-013 | W15: MKT-013.png
A16: 14 | B16: Light Yagami, front view | C16: Xianyu | D16: 【【出】death note快闪夜神月吧唧】 | E16: https://m.tb.cn/h.8glbxOP | F16: 46241 | G16: 60 | H16: Yes | J16: 0 | K16: =IF(OR(G16="",G16=0),"",G16+IF(I16="",0,I16)+IF(J16="",0,J16)) -> 60 | L16: 1 | M16: =IF(OR(K16="",L16=0),"",K16/L16) -> 60 | N16: My Dear Light | O16: Φ56mm matte | P16: Sealed, new | Q16: Yes | R16: No | S16: No | T16: Yes | V16: MKT-014 | W16: MKT-014.png
A17: 15 | B17: Light Yagami, front view | C17: Xianyu | D17: 【【出】名古屋快闪死亡笔记】 | E17: https://m.tb.cn/h.8TobcaQ | F17: 46241 | G17: 63 | H17: Yes | J17: 0 | K17: =IF(OR(G17="",G17=0),"",G17+IF(I17="",0,I17)+IF(J17="",0,J17)) -> 63 | L17: 1 | M17: =IF(OR(K17="",L17=0),"",K17/L17) -> 63 | N17: My Dear Light | O17: Φ56mm matte | P17: Opened, good condition | Q17: Yes | R17: No | S17: No | T17: Yes | V17: MKT-015 | W17: MKT-015.png
A18: 16 | B18: Misa Amane, smiling | C18: Xianyu | D18: 【夜神月弥海砂吧唧，线下db产物，皆有原袋，不包官伤，两个70】 | E18: https://m.tb.cn/h.8hZl5VV | F18: 46241 | G18: 70 | H18: Yes | J18: 0 | K18: =IF(OR(G18="",G18=0),"",G18+IF(I18="",0,I18)+IF(J18="",0,J18)) -> 70 | L18: 2 | M18: =IF(OR(K18="",L18=0),"",K18/L18) -> 35 | N18: My Dear Light | O18: Φ56mm matte | P18: Opened, good condition | Q18: No | R18: Yes | S18: No | T18: No | U18: Bundled sale; unit price unclear | V18: MKT-016 | W18: MKT-016.png
A19: 17 | B19: L, dark-gray profile | C19: Xianyu | D19: 【死亡笔记L侧脸吧唧，名古屋快闪限定款】 | E19: https://m.tb.cn/h.8hZSrSv | F19: 46241 | G19: 64.4 | H19: Yes | J19: 0 | K19: =IF(OR(G19="",G19=0),"",G19+IF(I19="",0,I19)+IF(J19="",0,J19)) -> 64.4 | L19: 1 | M19: =IF(OR(K19="",L19=0),"",K19/L19) -> 64.4 | N19: My Dear Light | O19: Φ56mm matte | P19: Sealed, new | Q19: Yes | R19: No | S19: No | T19: Yes | V19: MKT-017 | W19: MKT-017.png
A20: 18 | B20: L, dark-gray profile | C20: Xianyu | D20: 【DNL侧脸吧唧】 | E20: https://m.tb.cn/h.8gl2SyE | F20: 46241 | G20: 60 | H20: No | I20: 6 | J20: 0 | K20: =IF(OR(G20="",G20=0),"",G20+IF(I20="",0,I20)+IF(J20="",0,J20)) -> 66 | L20: 1 | M20: =IF(OR(K20="",L20=0),"",K20/L20) -> 66 | N20: My Dear Light | O20: Φ56mm matte | P20: Opened, good condition | Q20: Yes | R20: No | S20: No | T20: Yes | V20: MKT-018 | W20: MKT-018.png
A21: 19 | B21: L, dark-gray profile | C21: Xianyu | D21: 【Death Note L侧脸吧唧 正版】 | E21: https://m.tb.cn/h.8To2L35 | F21: 46241 | G21: 45 | H21: Yes | J21: 0 | K21: =IF(OR(G21="",G21=0),"",G21+IF(I21="",0,I21)+IF(J21="",0,J21)) -> 45 | L21: 1 | M21: =IF(OR(K21="",L21=0),"",K21/L21) -> 45 | N21: My Dear Light | O21: Φ56mm matte | P21: Opened, good condition | Q21: Yes | R21: No | S21: No | T21: Yes | V21: MKT-019 | W21: MKT-019.png
A22: 20 | B22: L, light-gray portrait | C22: Xianyu | D22: 【DEATHNOTE DN名古屋快闪L吧唧】 | E22: https://m.tb.cn/h.8hawTxv | F22: 46241 | G22: 45 | H22: Yes | J22: 0 | K22: =IF(OR(G22="",G22=0),"",G22+IF(I22="",0,I22)+IF(J22="",0,J22)) -> 45 | L22: 1 | M22: =IF(OR(K22="",L22=0),"",K22/L22) -> 45 | N22: My Dear Light | O22: Φ56mm matte | P22: Opened, good condition | Q22: Yes | R22: No | S22: No | T22: Yes | V22: MKT-020 | W22: MKT-020.png
A23: 21 | B23: L, light-gray portrait | C23: Xianyu | D23: 【死亡笔记 L 名古屋吧唧】 | E23: https://m.tb.cn/h.7gPLTuJ | F23: 2026-08-07 | G23: 60 | H23: Yes | J23: 0 | K23: =IF(OR(G23="",G23=0),"",G23+IF(I23="",0,I23)+IF(J23="",0,J23)) -> 60 | L23: 1 | M23: =IF(OR(K23="",L23=0),"",K23/L23) -> 60 | N23: My Dear Light | O23: Φ56mm matte | P23: Opened, good condition | Q23: Yes | R23: No | S23: No | T23: Yes | V23: MKT-021 | W23: MKT-021.png
A24: 22 | B24: L, dark-gray profile | C24: Xianyu | D24: 【死亡笔记 L 名古屋吧唧】 | E24: https://m.tb.cn/h.8gPLTuJ | F24: 2026-08-08 | G24: 46 | H24: Yes | J24: 0 | K24: =IF(OR(G24="",G24=0),"",G24+IF(I24="",0,I24)+IF(J24="",0,J24)) -> 46 | L24: 1 | M24: =IF(OR(K24="",L24=0),"",K24/L24) -> 46 | N24: My Dear Light | O24: Φ56mm matte | P24: Sealed, new | Q24: Yes | R24: No | S24: No | T24: Yes | V24: MKT-022 | W24: MKT-022.png
A25: 23 | B25: L, light-gray portrait | C25: Xianyu | D25: 【全新L名古屋快闪吧唧，死亡笔记角色L，线下抽的，有原袋，保存】 | E25: https://m.tb.cn/h.8hawF47 | F25: 2026-08-08 | G25: 49 | H25: No | I25: 12 | J25: 0 | K25: =IF(OR(G25="",G25=0),"",G25+IF(I25="",0,I25)+IF(J25="",0,J25)) -> 61 | L25: 1 | M25: =IF(OR(K25="",L25=0),"",K25/L25) -> 61 | N25: My Dear Light | O25: Φ56mm matte | P25: Opened, good condition | Q25: Yes | R25: No | S25: No | T25: Yes | V25: MKT-023 | W25: MKT-023.png
A26: 24 | B26: L, light-gray portrait | C26: Xianyu | D26: 【死亡笔记L名古屋快闪吧唧】 | E26: https://m.tb.cn/h.8TMobzc | F26: 2026-08-08 | G26: 52 | H26: Yes | J26: 0 | K26: =IF(OR(G26="",G26=0),"",G26+IF(I26="",0,I26)+IF(J26="",0,J26)) -> 52 | L26: 1 | M26: =IF(OR(K26="",L26=0),"",K26/L26) -> 52 | N26: My Dear Light | O26: Φ56mm matte | P26: Opened, good condition | Q26: Yes | R26: No | S26: No | T26: Yes | V26: MKT-024 | W26: MKT-024.png
A27: 25 | B27: L, light-gray portrait | C27: Xianyu | D27: 【死亡笔记名古屋快闪吧唧L】 | E27: https://m.tb.cn/h.8TMokXh | F27: 2026-08-08 | G27: 76 | H27: Yes | J27: 0 | K27: =IF(OR(G27="",G27=0),"",G27+IF(I27="",0,I27)+IF(J27="",0,J27)) -> 76 | L27: 1 | M27: =IF(OR(K27="",L27=0),"",K27/L27) -> 76 | N27: My Dear Light | O27: Φ56mm matte | P27: Opened, good condition | Q27: Yes | R27: No | S27: No | T27: Yes | V27: MKT-025 | W27: MKT-025.png
A28: 26 | B28: L, light-gray portrait | C28: Xianyu | D28: 【【出】死亡笔记 deathnote 名古屋快闪原画磨砂吧唧 有原】 | E28: https://m.tb.cn/h.8haxvWj | F28: 2026-08-08 | G28: 55 | H28: No | I28: 6 | J28: 0 | K28: =IF(OR(G28="",G28=0),"",G28+IF(I28="",0,I28)+IF(J28="",0,J28)) -> 61 | L28: 1 | M28: =IF(OR(K28="",L28=0),"",K28/L28) -> 61 | N28: My Dear Light | O28: Φ56mm matte | P28: Opened, good condition | Q28: Yes | R28: No | S28: No | T28: Yes | V28: MKT-026 | W28: MKT-026.png
A29: 27 | B29: L, light-gray portrait | C29: Xianyu | D29: 【死亡笔记 名古屋快闪 池袋快闪 parco 吧唧】 | E29: https://m.tb.cn/h.8TMpM3x | F29: 2026-08-08 | G29: 45 | H29: Yes | J29: 0 | K29: =IF(OR(G29="",G29=0),"",G29+IF(I29="",0,I29)+IF(J29="",0,J29)) -> 45 | L29: 1 | M29: =IF(OR(K29="",L29=0),"",K29/L29) -> 45 | N29: My Dear Light | O29: Φ56mm matte | P29: Condition not specified | Q29: Yes | R29: No | S29: No | T29: Yes | V29: MKT-027 | W29: MKT-027.png
A30: 28 | B30: L, light-gray portrait | C30: Xianyu | D30: 【【出】死亡笔记deathnote名古屋快闪原画磨砂吧唧 有原】 | E30: https://m.tb.cn/h.85lUsxU | F30: 2026-08-08 | G30: 60 | H30: Yes | J30: 0 | K30: =IF(OR(G30="",G30=0),"",G30+IF(I30="",0,I30)+IF(J30="",0,J30)) -> 60 | L30: 1 | M30: =IF(OR(K30="",L30=0),"",K30/L30) -> 60 | N30: My Dear Light | O30: Φ56mm matte | P30: Opened, good condition | Q30: Yes | R30: No | S30: No | T30: Yes | V30: MKT-028 | W30: MKT-028.png
A31: 29 | B31: L, light-gray portrait | C31: Xianyu | D31: 【【出】死亡笔记池袋快闪吧唧 L】 | E31: https://m.tb.cn/h.85l5KPI | F31: 2026-08-08 | G31: 55 | H31: No | I31: 10 | J31: 0 | K31: =IF(OR(G31="",G31=0),"",G31+IF(I31="",0,I31)+IF(J31="",0,J31)) -> 65 | L31: 1 | M31: =IF(OR(K31="",L31=0),"",K31/L31) -> 65 | N31: My Dear Light | O31: Φ56mm matte | P31: Condition not specified | Q31: Yes | R31: No | S31: No | T31: Yes | V31: MKT-029 | W31: MKT-029.png
A32: 30 | B32: L, light-gray portrait | C32: Xianyu | D32: 【出死亡笔记L原画吧唧4个150r】 | E32: https://m.tb.cn/h.8glcWxM | F32: 2026-08-08 | G32: 150 | H32: No | I32: 5 | J32: 0 | K32: =IF(OR(G32="",G32=0),"",G32+IF(I32="",0,I32)+IF(J32="",0,J32)) -> 155 | L32: 4 | M32: =IF(OR(K32="",L32=0),"",K32/L32) -> 38.75 | N32: My Dear Light | O32: Φ56mm matte | P32: Condition not specified | Q32: No | R32: Yes | S32: No | T32: Yes | V32: MKT-030 | W32: MKT-030.png
A33: 31 | B33: Misa Amane, smiling | C33: Xianyu | D33: 【出 dn名古屋L，弥海砂，梅洛吧唧，都有原袋】 | E33: https://m.tb.cn/h.8To48w5 | F33: 2026-08-06 | G33: 40 | H33: No | I33: 12 | K33: =IF(OR(G33="",G33=0),"",G33+IF(I33="",0,I33)+IF(J33="",0,J33)) -> 52 | L33: 1 | M33: =IF(OR(K33="",L33=0),"",K33/L33) -> 52 | N33: My Dear Light | O33: Φ56mm matte | P33: Sealed, new / original bag | Q33: No | R33: Yes | S33: No | T33: Yes | V33: MKT-031 | W33: MKT-031.png
A34: 32 | B34: L, light-gray portrait | C34: Xianyu | D34: 【出 dn名古屋L，弥海砂，梅洛吧唧，都有原袋】 | E34: https://m.tb.cn/h.8To48w6 | F34: 2026-08-07 | G34: 60 | H34: No | I34: 12 | K34: =IF(OR(G34="",G34=0),"",G34+IF(I34="",0,I34)+IF(J34="",0,J34)) -> 72 | L34: 1 | M34: =IF(OR(K34="",L34=0),"",K34/L34) -> 72 | N34: My Dear Light | O34: Φ56mm matte | P34: Sealed, new / original bag | Q34: No | R34: Yes | S34: No | T34: Yes | V34: MKT-032 | W34: MKT-032.png
A35: 33 | B35: Mello | C35: Xianyu | D35: 【出 dn名古屋L，弥海砂，梅洛吧唧，都有原袋】 | E35: https://m.tb.cn/h.8To48w7 | F35: 2026-08-08 | G35: 30 | H35: No | I35: 12 | J35: 0 | K35: =IF(OR(G35="",G35=0),"",G35+IF(I35="",0,I35)+IF(J35="",0,J35)) -> 42 | L35: 1 | M35: =IF(OR(K35="",L35=0),"",K35/L35) -> 42 | N35: My Dear Light | O35: Φ56mm matte | P35: Sealed, new / original bag | Q35: No | R35: Yes | S35: No | T35: No | U35: Bundled sale; unit price unclear | V35: MKT-033 | W35: MKT-033.png
A36: 34 | B36: Misa Amane, choker | C36: Xianyu | D36: 【死亡笔记 弥海砂名古屋快闪原画吧唧，全新未拆，有原包装。日版】 | E36: https://m.tb.cn/h.85lka0J | F36: 2026-08-08 | G36: 35 | H36: Yes | J36: 0 | K36: =IF(OR(G36="",G36=0),"",G36+IF(I36="",0,I36)+IF(J36="",0,J36)) -> 35 | L36: 1 | M36: =IF(OR(K36="",L36=0),"",K36/L36) -> 35 | N36: My Dear Light | O36: Φ56mm matte | P36: Sealed, new / original bag | Q36: Yes | R36: No | S36: No | T36: Yes | V36: MKT-034 | W36: MKT-034.png
A37: 35 | B37: Misa Amane, choker | C37: Xianyu | D37: 【弥海砂名古屋快闪吧唧 总共标价11个】 | E37: https://m.tb.cn/h.8hZelaw | F37: 2026-08-08 | J37: 0 | K37: =IF(OR(G37="",G37=0),"",G37+IF(I37="",0,I37)+IF(J37="",0,J37)) | L37: 1 | M37: =IF(OR(K37="",L37=0),"",K37/L37) | N37: My Dear Light | O37: Φ56mm matte | P37: Condition not specified | Q37: Yes | R37: No | S37: No | T37: Yes | V37: MKT-035 | W37: MKT-035.png
A38: 36 | B38: Misa Amane, choker | C38: Xianyu | D38: 【死亡笔记弥海砂吧唧】 | E38: https://m.tb.cn/h.8TMC7lv | F38: 2026-08-08 | G38: 50 | H38: No | I38: 10 | J38: 0 | K38: =IF(OR(G38="",G38=0),"",G38+IF(I38="",0,I38)+IF(J38="",0,J38)) -> 60 | L38: 1 | M38: =IF(OR(K38="",L38=0),"",K38/L38) -> 60 | N38: My Dear Light | O38: Φ56mm matte | P38: Opened, good condition | Q38: Yes | R38: No | S38: No | T38: Yes | V38: MKT-036 | W38: MKT-036.png
A39: 37 | B39: Misa Amane, smiling | C39: Xianyu | D39: 【出】deathnote死亡笔记，弥海砂misa名古屋吧唧】 | E39: https://m.tb.cn/h.85lrZ1E | F39: 2026-08-08 | G39: 35 | H39: Yes | J39: 0 | K39: =IF(OR(G39="",G39=0),"",G39+IF(I39="",0,I39)+IF(J39="",0,J39)) -> 35 | L39: 1 | M39: =IF(OR(K39="",L39=0),"",K39/L39) -> 35 | N39: My Dear Light | O39: Φ56mm matte | P39: Opened, good condition | Q39: Yes | R39: No | S39: No | T39: Yes | V39: MKT-037 | W39: MKT-037.png
A40: 38 | B40: Misa Amane, smiling | C40: Xianyu | D40: 【出 死亡笔记 dn名古屋弥海砂吧唧】 | E40: https://m.tb.cn/h.8To3Rip | F40: 2026-08-08 | G40: 35.12 | H40: No | I40: 10 | J40: 0 | K40: =IF(OR(G40="",G40=0),"",G40+IF(I40="",0,I40)+IF(J40="",0,J40)) -> 45.12 | L40: 1 | M40: =IF(OR(K40="",L40=0),"",K40/L40) -> 45.12 | N40: My Dear Light | O40: Φ56mm matte | P40: Opened, good condition | Q40: Yes | R40: No | S40: No | T40: Yes | V40: MKT-038 | W40: MKT-038.png
A41: 39 | B41: Misa Amane, smiling | C41: Xianyu | D41: 【deathnote弥海砂misa名古屋吧唧】 | E41: https://m.tb.cn/h.8hZk6KB | F41: 2026-08-08 | G41: 37.6 | H41: Yes | J41: 0 | K41: =IF(OR(G41="",G41=0),"",G41+IF(I41="",0,I41)+IF(J41="",0,J41)) -> 37.6 | L41: 1 | M41: =IF(OR(K41="",L41=0),"",K41/L41) -> 37.6 | N41: My Dear Light | O41: Φ56mm matte | P41: Opened, good condition | Q41: Yes | R41: No | S41: No | T41: Yes | V41: MKT-039 | W41: MKT-039.png
A42: 40 | B42: Misa Amane, smiling | C42: Xianyu | D42: 【死亡笔记名古屋快闪吧唧 弥海砂】 | E42: https://m.tb.cn/h.8hZknNa | F42: 2026-08-08 | G42: 31 | H42: No | I42: 6.9 | J42: 0 | K42: =IF(OR(G42="",G42=0),"",G42+IF(I42="",0,I42)+IF(J42="",0,J42)) -> 37.9 | L42: 1 | M42: =IF(OR(K42="",L42=0),"",K42/L42) -> 37.9 | N42: My Dear Light | O42: Φ56mm matte | P42: Slight defect | Q42: Yes | R42: No | S42: No | T42: Yes | V42: MKT-040 | W42: MKT-040.png
A43: 41 | B43: Misa Amane, smiling | C43: Xianyu | D43: 【出】dn名古屋弥海砂吧唧】 | E43: https://m.tb.cn/h.85lItEU | F43: 2026-08-08 | G43: 35 | I43: 6 | J43: 0 | K43: =IF(OR(G43="",G43=0),"",G43+IF(I43="",0,I43)+IF(J43="",0,J43)) -> 41 | L43: 1 | M43: =IF(OR(K43="",L43=0),"",K43/L43) -> 41 | N43: My Dear Light | O43: Φ56mm matte | P43: Opened, good condition | Q43: Yes | R43: No | S43: No | T43: Yes | V43: MKT-041 | W43: MKT-041.png
A44: 42 | B44: Misa Amane, smiling | C44: Xianyu | D44: 【标价直拍】DN名古屋 弥海砂吧唧】 | E44: https://m.tb.cn/h.8hZPjYT | F44: 2026-08-08 | G44: 30.18 | H44: No | I44: 12 | J44: 0 | K44: =IF(OR(G44="",G44=0),"",G44+IF(I44="",0,I44)+IF(J44="",0,J44)) -> 42.18 | L44: 1 | M44: =IF(OR(K44="",L44=0),"",K44/L44) -> 42.18 | N44: My Dear Light | O44: Φ56mm matte | P44: Opened, good condition | Q44: Yes | R44: No | S44: No | T44: Yes | V44: MKT-042 | W44: MKT-042.png
A45: 43 | B45: L, dark-gray profile | C45: Xianyu | D45: 【出】死亡笔记 dn名古屋快闪限定吧唧 弥海砂 L】 | E45: https://m.tb.cn/h.85lH4Br | F45: 2026-08-07 | G45: 45 | H45: No | I45: 7 | K45: =IF(OR(G45="",G45=0),"",G45+IF(I45="",0,I45)+IF(J45="",0,J45)) -> 52 | L45: 1 | M45: =IF(OR(K45="",L45=0),"",K45/L45) -> 52 | N45: My Dear Light | O45: Φ56mm matte | P45: Opened, good condition | Q45: Yes | R45: No | S45: No | T45: Yes | V45: MKT-043 | W45: MKT-043.png
A46: 44 | B46: Misa Amane, choker | C46: Xianyu | D46: 【出】死亡笔记 dn名古屋快闪限定吧唧 弥海砂 L】 | E46: https://m.tb.cn/h.85lH5Br | F46: 2026-08-08 | G46: 25 | H46: No | I46: 7 | J46: 0 | K46: =IF(OR(G46="",G46=0),"",G46+IF(I46="",0,I46)+IF(J46="",0,J46)) -> 32 | L46: 1 | M46: =IF(OR(K46="",L46=0),"",K46/L46) -> 32 | N46: My Dear Light | O46: Φ56mm matte | P46: Opened, good condition | Q46: Yes | R46: No | S46: No | T46: Yes | V46: MKT-044 | W46: MKT-044.png
A47: 45 | B47: Near | C47: Xianyu | D47: 【包邮出】死亡笔记 尼亚名古屋快闪原画吧唧 日版正品】 | E47: https://m.tb.cn/h.8hZ1K1W | F47: 2026-08-08 | G47: 14.08 | H47: Yes | I47: 0 | J47: 0 | K47: =IF(OR(G47="",G47=0),"",G47+IF(I47="",0,I47)+IF(J47="",0,J47)) -> 14.08 | L47: 1 | M47: =IF(OR(K47="",L47=0),"",K47/L47) -> 14.08 | N47: My Dear Light | O47: Φ56mm matte | P47: Opened, good condition | Q47: Yes | R47: No | S47: No | T47: Yes | V47: MKT-045 | W47: MKT-045.png
A48: 46 | B48: Near | C48: Xianyu | D48: 【【国现】死亡笔记 尼亚 池袋parco吧唧】 | E48: https://m.tb.cn/h.8hZ1foc | F48: 2026-08-08 | G48: 9.6 | H48: No | I48: 8 | J48: 0 | K48: =IF(OR(G48="",G48=0),"",G48+IF(I48="",0,I48)+IF(J48="",0,J48)) -> 17.6 | L48: 1 | M48: =IF(OR(K48="",L48=0),"",K48/L48) -> 17.6 | N48: My Dear Light | O48: Φ56mm matte | P48: Opened, good condition | Q48: Yes | R48: No | S48: No | T48: Yes | V48: MKT-046 | W48: MKT-046.png
A49: 47 | B49: Near | C49: Xianyu | D49: 【死亡笔记名古屋快闪 尼亚】 | E49: https://m.tb.cn/h.8hZ1CJu | F49: 2026-08-08 | G49: 20.33 | H49: Yes | J49: 0 | K49: =IF(OR(G49="",G49=0),"",G49+IF(I49="",0,I49)+IF(J49="",0,J49)) -> 20.33 | L49: 1 | M49: =IF(OR(K49="",L49=0),"",K49/L49) -> 20.33 | N49: My Dear Light | O49: Φ56mm matte | P49: Opened, good condition | Q49: Yes | R49: No | S49: No | T49: Yes | V49: MKT-047 | W49: MKT-047.png
A50: 48 | B50: Near | C50: Xianyu | D50: 【【出】death+note+死亡笔记尼亚名古屋快闪吧唧】 | E50: https://m.tb.cn/h.8gPFmmg | F50: 2026-08-08 | G50: 20 | H50: Yes | J50: 0 | K50: =IF(OR(G50="",G50=0),"",G50+IF(I50="",0,I50)+IF(J50="",0,J50)) -> 20 | L50: 1 | M50: =IF(OR(K50="",L50=0),"",K50/L50) -> 20 | N50: My Dear Light | O50: Φ56mm matte | P50: Opened, good condition | Q50: Yes | R50: No | S50: No | T50: Yes | V50: MKT-048 | W50: MKT-048.png
A51: 49 | B51: Near | C51: Xianyu | D51: 【死亡笔记尼亚角色名古屋快闪限定吧唧，原袋封装，表面无磨损】 | E51: https://m.tb.cn/h.8TMFYvq | F51: 2026-08-08 | G51: 24.88 | H51: Yes | J51: 0 | K51: =IF(OR(G51="",G51=0),"",G51+IF(I51="",0,I51)+IF(J51="",0,J51)) -> 24.88 | L51: 1 | M51: =IF(OR(K51="",L51=0),"",K51/L51) -> 24.88 | N51: My Dear Light | O51: Φ56mm matte | P51: Sealed, new / original bag | Q51: Yes | R51: No | S51: No | T51: Yes | V51: MKT-049 | W51: MKT-049.png
A52: 50 | B52: Near | C52: Xianyu | D52: 【【出】尼亚名古屋快闪吧唧】 | E52: https://m.tb.cn/h.8gPFpp3 | F52: 2026-08-08 | G52: 10 | H52: No | I52: 12 | J52: 0 | K52: =IF(OR(G52="",G52=0),"",G52+IF(I52="",0,I52)+IF(J52="",0,J52)) -> 22 | L52: 1 | M52: =IF(OR(K52="",L52=0),"",K52/L52) -> 22 | N52: My Dear Light | O52: Φ56mm matte | P52: Opened, good condition | Q52: Yes | R52: No | S52: No | T52: Yes | V52: MKT-050 | W52: MKT-050.png
A53: 51 | B53: Near | C53: Xianyu | D53: 【【包邮出】死亡笔记 尼亚 池袋parco吧唧】 | E53: https://m.tb.cn/h.8TMv6ks | F53: 2026-08-08 | G53: 20 | H53: Yes | I53: 0 | J53: 0 | K53: =IF(OR(G53="",G53=0),"",G53+IF(I53="",0,I53)+IF(J53="",0,J53)) -> 20 | L53: 1 | M53: =IF(OR(K53="",L53=0),"",K53/L53) -> 20 | N53: My Dear Light | O53: Φ56mm matte | P53: Opened, good condition | Q53: Yes | R53: No | S53: No | T53: Yes | V53: MKT-051 | W53: MKT-051.png
A54: 52 | B54: Mello | C54: Xianyu | D54: 【出】尼亚 M praco快闪 正脸吧唧】 | E54: https://m.tb.cn/h.8hZ1jhd | F54: 2026-08-07 | G54: 10 | H54: Yes | K54: =IF(OR(G54="",G54=0),"",G54+IF(I54="",0,I54)+IF(J54="",0,J54)) -> 10 | L54: 1 | M54: =IF(OR(K54="",L54=0),"",K54/L54) -> 10 | N54: My Dear Light | O54: Φ56mm matte | P54: Opened, good condition | Q54: Yes | R54: No | S54: No | T54: No | U54: Bundled sale; unit price unclear | V54: MKT-052 | W54: MKT-052.png
A55: 53 | B55: Near | C55: Xianyu | D55: 【出】尼亚 M praco快闪 正脸吧唧】 | E55: https://m.tb.cn/h.8hZ2jhd | F55: 2026-08-08 | G55: 20 | H55: Yes | J55: 0 | K55: =IF(OR(G55="",G55=0),"",G55+IF(I55="",0,I55)+IF(J55="",0,J55)) -> 20 | L55: 1 | M55: =IF(OR(K55="",L55=0),"",K55/L55) -> 20 | N55: My Dear Light | O55: Φ56mm matte | P55: Opened, good condition | Q55: Yes | R55: No | S55: No | T55: Yes | V55: MKT-053 | W55: MKT-053.png
A56: 54 | B56: Near | C56: Xianyu | D56: 【Death Note周边 日谷 名古屋快闪吧唧 尼亚】 | E56: https://m.tb.cn/h.8gPwdCB | F56: 2026-08-08 | G56: 18 | H56: No | I56: 12 | J56: 0 | K56: =IF(OR(G56="",G56=0),"",G56+IF(I56="",0,I56)+IF(J56="",0,J56)) -> 30 | L56: 1 | M56: =IF(OR(K56="",L56=0),"",K56/L56) -> 30 | N56: My Dear Light | O56: Φ56mm matte | P56: Opened, good condition | Q56: Yes | R56: No | S56: No | T56: Yes | V56: MKT-054 | W56: MKT-054.png
A57: 55 | B57: Near | C57: Xianyu | D57: 【【现货包邮】死亡笔记名古屋快闪吧唧 尼亚款，日谷出品。全新未】 | E57: https://m.tb.cn/h.8hZdtsP | F57: 2026-08-08 | G57: 15 | H57: No | I57: 12 | J57: 0 | K57: =IF(OR(G57="",G57=0),"",G57+IF(I57="",0,I57)+IF(J57="",0,J57)) -> 27 | L57: 1 | M57: =IF(OR(K57="",L57=0),"",K57/L57) -> 27 | N57: My Dear Light | O57: Φ56mm matte | P57: Sealed, new / original bag | Q57: Yes | R57: No | S57: No | T57: Yes | V57: MKT-055 | W57: MKT-055.png
A58: 56 | B58: Near | C58: Xianyu | D58: 【【出】死亡笔记尼亚快闪吧唧】 | E58: https://m.tb.cn/h.85l9YGK | F58: 2026-08-08 | G58: 25 | H58: No | I58: 6 | J58: 0 | K58: =IF(OR(G58="",G58=0),"",G58+IF(I58="",0,I58)+IF(J58="",0,J58)) -> 31 | L58: 1 | M58: =IF(OR(K58="",L58=0),"",K58/L58) -> 31 | N58: My Dear Light | O58: Φ56mm matte | P58: Condition not specified | Q58: Yes | R58: No | S58: No | T58: Yes | V58: MKT-056 | W58: MKT-056.png
A59: 57 | B59: Near | C59: Xianyu | D59: 【【出】死亡笔记 deathnote名古屋池袋快闪吧唧 尼亚】 | E59: https://m.tb.cn/h.85lQCY0 | F59: 2026-08-08 | G59: 15 | H59: No | I59: 5 | J59: 0 | K59: =IF(OR(G59="",G59=0),"",G59+IF(I59="",0,I59)+IF(J59="",0,J59)) -> 20 | L59: 1 | M59: =IF(OR(K59="",L59=0),"",K59/L59) -> 20 | N59: My Dear Light | O59: Φ56mm matte | P59: Opened, good condition | Q59: Yes | R59: No | S59: No | T59: Yes | V59: MKT-057 | W59: MKT-057.png
A60: 58 | B60: Misa Amane, choker | C60: Xianyu | D60: 【出 / 换】尼亚 / 弥海砂misa名古屋快闪，包非偏。可换L或梅】 | E60: https://m.tb.cn/h.7TMAbor | F60: 2026-08-07 | G60: 35 | H60: Yes | K60: =IF(OR(G60="",G60=0),"",G60+IF(I60="",0,I60)+IF(J60="",0,J60)) -> 35 | L60: 1 | M60: =IF(OR(K60="",L60=0),"",K60/L60) -> 35 | N60: My Dear Light | O60: Φ56mm matte | P60: Opened, good condition | Q60: Yes | R60: No | S60: No | T60: Yes | V60: MKT-058 | W60: MKT-058.png
A61: 59 | B61: Near | C61: Xianyu | D61: 【出 / 换】尼亚 / 弥海砂misa名古屋快闪，包非偏。可换L或梅】 | E61: https://m.tb.cn/h.8TMAbor | F61: 2026-08-08 | G61: 20 | H61: Yes | J61: 0 | K61: =IF(OR(G61="",G61=0),"",G61+IF(I61="",0,I61)+IF(J61="",0,J61)) -> 20 | L61: 1 | M61: =IF(OR(K61="",L61=0),"",K61/L61) -> 20 | N61: My Dear Light | O61: Φ56mm matte | P61: Opened, good condition | Q61: Yes | R61: No | S61: No | T61: Yes | V61: MKT-059 | W61: MKT-059.png
A62: 60 | B62: Misa Amane, smiling | C62: Xianyu | D62: 【国现可直拍包非偏】死亡笔记名古屋快闪徽章 弥海砂正脸吧唧 | E62: https://m.tb.cn/h.8h8sTgw | F62: 46248 | G62: 35 | H62: No | I62: 8 | J62: 0 | K62: =IF(A62="","",G62+I62+J62) -> 43 | L62: 1 | M62: =IF(A62="","",IFERROR(K62/L62,"")) -> 43 | N62: My Dear Light | O62: Φ56mm matte | P62: Opened, good condition | Q62: Yes | R62: No | S62: No | T62: Yes | V62: MKT-060 | W62: MKT-060.png
A63: 61 | B63: Near | C63: Xianyu | D63: 【国现可直拍包非偏】死亡笔记名古屋快闪徽章 弥海砂正脸吧唧 | E63: https://m.tb.cn/h.8h9sTgw | F63: 46248 | G63: 25 | H63: No | I63: 8 | J63: 0 | K63: =IF(A63="","",G63+I63+J63) -> 33 | L63: 1 | M63: =IF(A63="","",IFERROR(K63/L63,"")) -> 33 | N63: My Dear Light | O63: Φ56mm matte | P63: Opened, good condition | Q63: Yes | R63: No | S63: No | T63: Yes | V63: MKT-061 | W63: MKT-061.png
A64: 62 | B64: Light Yagami, profile | C64: Xianyu | D64: 死亡笔记 夜神月名古屋快闪吧唧 | E64: https://m.tb.cn/h.8h8uM3E | F64: 46248 | G64: 50 | H64: Yes | I64: 0 | J64: 0 | K64: =IF(A64="","",G64+I64+J64) -> 50 | L64: 1 | M64: =IF(A64="","",IFERROR(K64/L64,"")) -> 50 | N64: My Dear Light | O64: Φ56mm matte | P64: Opened, good condition | Q64: Yes | R64: No | S64: No | T64: Yes | V64: MKT-062 | W64: MKT-062.png
A65: 63 | B65: Light Yagami, front view | C65: Xianyu | D65: 死亡笔记 夜神月名古屋快闪吧唧 | E65: https://m.tb.cn/h.8h8uM4E | F65: 46248 | G65: 50 | H65: Yes | I65: 0 | J65: 0 | K65: =IF(A65="","",G65+I65+J65) -> 50 | L65: 1 | M65: =IF(A65="","",IFERROR(K65/L65,"")) -> 50 | N65: My Dear Light | O65: Φ56mm matte | P65: Opened, good condition | Q65: Yes | R65: No | S65: No | T65: Yes | V65: MKT-063 | W65: MKT-063.png
A66: 64 | B66: Light Yagami, profile | C66: Xianyu | D66: 【可直拍】死亡笔记名古屋快闪吧唧 夜神月 | E66: https://m.tb.cn/h.8iBaM4L | F66: 46247 | G66: 45 | H66: Yes | I66: 0 | J66: 0 | K66: =IF(A66="","",G66+I66+J66) -> 45 | L66: 1 | M66: =IF(A66="","",IFERROR(K66/L66,"")) -> 45 | N66: My Dear Light | O66: Φ56mm matte | P66: Opened, good condition | Q66: Yes | R66: No | S66: No | T66: Yes | V66: MKT-064 | W66: MKT-064.png
A67: 65 | B67: Light Yagami, front view | C67: Xianyu | D67: 【可直拍】死亡笔记名古屋快闪吧唧 夜神月 | E67: https://m.tb.cn/h.8iBaM5L | F67: 46248 | G67: 45 | H67: Yes | I67: 0 | J67: 0 | K67: =IF(A67="","",G67+I67+J67) -> 45 | L67: 1 | M67: =IF(A67="","",IFERROR(K67/L67,"")) -> 45 | N67: My Dear Light | O67: Φ56mm matte | P67: Opened, good condition | Q67: Yes | R67: No | S67: No | T67: Yes | V67: MKT-065 | W67: MKT-065.png
A68: 66 | B68: Light Yagami, front view | C68: Xianyu | D68: 【包邮】死亡笔记名古屋快闪 | E68: https://m.tb.cn/h.8iBZjh0 | F68: 46248 | G68: 69.9 | H68: Yes | I68: 0 | J68: 0 | K68: =IF(A68="","",G68+I68+J68) -> 69.9 | L68: 1 | M68: =IF(A68="","",IFERROR(K68/L68,"")) -> 69.9 | N68: My Dear Light | O68: Φ56mm matte | P68: Opened, good condition | Q68: No | R68: No | S68: No | T68: Yes | V68: MKT-066 | W68: MKT-066.png
A69: 67 | B69: Light Yagami, front view | C69: Xianyu | D69: 【出】名古屋快闪死亡笔记 | E69: https://m.tb.cn/h.8iBZ5GM | F69: 46248 | G69: 63 | H69: Yes | I69: 0 | J69: 0 | K69: =IF(A69="","",G69+I69+J69) -> 63 | L69: 1 | M69: =IF(A69="","",IFERROR(K69/L69,"")) -> 63 | N69: My Dear Light | O69: Φ56mm matte | P69: Opened, good condition | Q69: No | R69: No | S69: No | T69: Yes | V69: MKT-067 | W69: MKT-067.png
A70: 68 | B70: L, light-gray portrait | C70: Xianyu | D70: 【全新L名古屋快闪吧唧，死亡笔记 | E70: https://m.tb.cn/h.8h8wStM | F70: 46248 | G70: 49 | H70: No | I70: 12 | J70: 0 | K70: =IF(A70="","",G70+I70+J70) -> 61 | L70: 1 | M70: =IF(A70="","",IFERROR(K70/L70,"")) -> 61 | N70: My Dear Light | O70: Φ56mm matte | P70: Opened, good condition | Q70: Yes | R70: No | S70: No | T70: Yes | V70: MKT-068 | W70: MKT-068.png
A71: 69 | B71: Misa Amane, smiling | C71: Xianyu | D71: 出 死亡笔记弥海砂吧唧 4枚90 | E71: https://m.tb.cn/h.7hjdpTT | F71: 46247 | G71: 22.5 | H71: No | I71: 5 | J71: 0 | K71: =IF(A71="","",G71+I71+J71) -> 27.5 | L71: 1 | M71: =IF(A71="","",IFERROR(K71/L71,"")) -> 27.5 | N71: My Dear Light | O71: Φ56mm matte | P71: Opened, good condition | Q71: Yes | R71: No | S71: No | T71: Yes | V71: MKT-069 | W71: MKT-069.png
A72: 70 | B72: Misa Amane, choker | C72: Xianyu | D72: 出 死亡笔记弥海砂吧唧 4枚90 | E72: https://m.tb.cn/h.8hjdpTT | F72: 46248 | G72: 22.5 | H72: No | I72: 5 | J72: 0 | K72: =IF(A72="","",G72+I72+J72) -> 27.5 | L72: 1 | M72: =IF(A72="","",IFERROR(K72/L72,"")) -> 27.5 | N72: My Dear Light | O72: Φ56mm matte | P72: Opened, good condition | Q72: Yes | R72: No | S72: No | T72: Yes | V72: MKT-070 | W72: MKT-070.png
A73: 71 | B73: Misa Amane, choker | C73: Xianyu | D73: 出【死亡笔记death note】名古屋快闪吧唧 | E73: https://m.tb.cn/h.8SR78Gp | F73: 46247 | G73: 30 | H73: No | I73: 8 | J73: 0 | K73: =IF(A73="","",G73+I73+J73) -> 38 | L73: 1 | M73: =IF(A73="","",IFERROR(K73/L73,"")) -> 38 | N73: My Dear Light | O73: Φ56mm matte | P73: Opened, good condition | Q73: Yes | R73: No | S73: No | T73: Yes | V73: MKT-071 | W73: MKT-071.png
... A79: 77 | B79: L, light-gray portrait | C79: Xianyu | D79: 名古屋快闪原画L正脸吧唧 有原袋 | E79: https://m.tb.cn/h.8iB1Vs7 | F79: 46248 | G79: 31 | H79: No | I79: 6 | J79: 0 | K79: =IF(A79="","",G79+I79+J79) -> 37 | L79: 1 | M79: =IF(A79="","",IFERROR(K79/L79,"")) -> 37 | N79: My Dear Light | O79: Φ56mm matte | P79: Opened, good condition | Q79: Yes | R79: No | S79: No | T79: Yes | V79: MKT-077 | W79: MKT-077.png
A80: 78 | B80: L, dark-gray profile | C80: Xianyu | D80: 死亡笔记 L侧脸吧唧，名古屋快闪限定款 | E80: https://m.tb.cn/h.8SsANYr | F80: 2026-08-14 | G80: 64.4 | H80: Yes | J80: 0 | K80: =IF(OR(G80="",G80=0),"",G80+IF(I80="",0,I80)+IF(J80="",0,J80)) -> 64.4 | L80: 1 | M80: =IF(OR(K80="",L80=0),"",K80/L80) -> 64.4 | N80: My Dear Light | O80: Φ56mm matte | P80: Opened, good condition | Q80: Yes | R80: No | S80: No | T80: Yes | V80: MKT-078 | W80: MKT-078.png
A81: 79 | B81: L, dark-gray profile | C81: Xianyu | D81: Death Note L侧脸吧唧 正版 | E81: https://m.tb.cn/h.8SHZ6VI | F81: 2026-08-14 | G81: 40 | H81: No | I81: 12 | J81: 0 | K81: =IF(OR(G81="",G81=0),"",G81+IF(I81="",0,I81)+IF(J81="",0,J81)) -> 52 | L81: 1 | M81: =IF(OR(K81="",L81=0),"",K81/L81) -> 52 | N81: My Dear Light | O81: Φ56mm matte | P81: Opened, good condition | Q81: Yes | R81: No | S81: No | T81: Yes | V81: MKT-079 | W81: MKT-079.png
A82: 80 | B82: L, dark-gray profile | C82: Xianyu | D82: 【帮诡秘挂】出 dn deathnote L 名古屋快闪店限定 | E82: https://m.tb.cn/h.8htvaF5 | F82: 2026-08-14 | G82: 50 | H82: No | I82: 7 | J82: 0 | K82: =IF(OR(G82="",G82=0),"",G82+IF(I82="",0,I82)+IF(J82="",0,J82)) -> 57 | L82: 1 | M82: =IF(OR(K82="",L82=0),"",K82/L82) -> 57 | N82: My Dear Light | O82: Φ56mm matte | P82: Opened, good condition | Q82: Yes | R82: No | S82: No | T82: Yes | V82: MKT-080 | W82: MKT-080.png
A83: 81 | B83: L, dark-gray profile | C83: Xianyu | D83: L侧脸吧唧 | E83: https://m.tb.cn/h.87DVwGw | F83: 2026-08-14 | G83: 75 | H83: Yes | J83: 0 | K83: =IF(OR(G83="",G83=0),"",G83+IF(I83="",0,I83)+IF(J83="",0,J83)) -> 75 | L83: 1 | M83: =IF(OR(K83="",L83=0),"",K83/L83) -> 75 | N83: My Dear Light | O83: Φ56mm matte | P83: Opened, good condition | Q83: Yes | R83: No | S83: No | T83: Yes | V83: MKT-081 | W83: MKT-081.png
A84: 82 | B84: Misa Amane, choker | C84: Xianyu | D84: 死亡笔记 弥海砂名古屋快闪原画吧唧，全新未拆，有原包装。日版 | E84: https://m.tb.cn/h.8RT59yw | F84: 2026-08-14 | G84: 35 | H84: Yes | J84: 0 | K84: =IF(OR(G84="",G84=0),"",G84+IF(I84="",0,I84)+IF(J84="",0,J84)) -> 35 | L84: 1 | M84: =IF(OR(K84="",L84=0),"",K84/L84) -> 35 | N84: My Dear Light | O84: Φ56mm matte | P84: Opened, good condition | Q84: Yes | R84: No | S84: No | T84: Yes | V84: MKT-082 | W84: MKT-082.png
A85: 83 | B85: Misa Amane, smiling | C85: Xianyu | D85: 【出】死亡笔记 弥海砂吧唧 | E85: https://m.tb.cn/h.8SHfaWd | F85: 2026-08-14 | G85: 23 | H85: No | I85: 12 | J85: 0 | K85: =IF(OR(G85="",G85=0),"",G85+IF(I85="",0,I85)+IF(J85="",0,J85)) -> 35 | L85: 1 | M85: =IF(OR(K85="",L85=0),"",K85/L85) -> 35 | N85: My Dear Light | O85: Φ56mm matte | P85: Opened, good condition | Q85: Yes | R85: No | S85: No | T85: Yes | V85: MKT-083 | W85: MKT-083.png
A86: 84 | B86: Misa Amane, choker | C86: Xianyu | D86: 【可直拍】死亡笔记弥海砂名古屋快闪原画吧唧 | E86: https://m.tb.cn/h.8SH2iZy | F86: 2026-08-14 | G86: 25 | H86: No | I86: 4 | J86: 0 | K86: =IF(OR(G86="",G86=0),"",G86+IF(I86="",0,I86)+IF(J86="",0,J86)) -> 29 | L86: 1 | M86: =IF(OR(K86="",L86=0),"",K86/L86) -> 29 | N86: My Dear Light | O86: Φ56mm matte | P86: Opened, good condition | Q86: Yes | R86: No | S86: No | T86: Yes | V86: MKT-084 | W86: MKT-084.png
A87: 85 | B87: Light Yagami, profile | C87: Xianyu | D87: 死亡笔记 名古屋快闪吧唧 夜神月 | E87: https://m.tb.cn/h.8RTa5G8 | F87: 2026-08-14 | G87: 56 | H87: Yes | J87: 0 | K87: =IF(OR(G87="",G87=0),"",G87+IF(I87="",0,I87)+IF(J87="",0,J87)) -> 56 | L87: 1 | M87: =IF(OR(K87="",L87=0),"",K87/L87) -> 56 | N87: My Dear Light | O87: Φ56mm matte | P87: Opened, good condition | Q87: Yes | R87: No | S87: No | T87: Yes | V87: MKT-085 | W87: MKT-085.png
A88: 86 | B88: Light Yagami, profile | C88: Xianyu | D88: 【出】死亡笔记 My Dear Light 快闪吧唧 夜神月 | E88: https://m.tb.cn/h.8SsCG8M | F88: 2026-08-14 | G88: 67 | H88: No | I88: 12 | J88: 0 | K88: =IF(OR(G88="",G88=0),"",G88+IF(I88="",0,I88)+IF(J88="",0,J88)) -> 79 | L88: 1 | M88: =IF(OR(K88="",L88=0),"",K88/L88) -> 79 | N88: My Dear Light | O88: Φ56mm matte | P88: Opened, good condition | Q88: Yes | R88: No | S88: No | T88: Yes | V88: MKT-086 | W88: MKT-086.png
A89: 87 | B89: Light Yagami, profile | C89: Xianyu | D89: 标价死亡笔记名古屋快闪夜神月侧脸 | E89: https://m.tb.cn/h.87Db9No | F89: 2026-08-14 | G89: 57 | H89: Yes | J89: 0 | K89: =IF(OR(G89="",G89=0),"",G89+IF(I89="",0,I89)+IF(J89="",0,J89)) -> 57 | L89: 1 | M89: =IF(OR(K89="",L89=0),"",K89/L89) -> 57 | N89: My Dear Light | O89: Φ56mm matte | P89: Opened, good condition | Q89: Yes | R89: No | S89: No | T89: Yes | V89: MKT-087 | W89: MKT-087.png
A90: 88 | B90: Light Yagami, profile | C90: Xianyu | D90: (可直拍) 出夜神月名古屋快闪吧唧一对110不包，原包装都在 | E90: https://m.tb.cn/h.8htKgX0 | F90: 2026-08-14 | G90: 55 | H90: No | I90: 6 | J90: 0 | K90: =IF(OR(G90="",G90=0),"",G90+IF(I90="",0,I90)+IF(J90="",0,J90)) -> 61 | L90: 1 | M90: =IF(OR(K90="",L90=0),"",K90/L90) -> 61 | N90: My Dear Light | O90: Φ56mm matte | P90: Opened, good condition | Q90: Yes | R90: No | S90: No | T90: Yes | V90: MKT-088 | W90: MKT-088.png
A91: 89 | B91: Light Yagami, profile | C91: Xianyu | D91: 【出】死亡笔记 My Dear Light 快闪吧唧 夜神月 | E91: https://m.tb.cn/h.8Ssxefc | F91: 2026-08-14 | G91: 58 | H91: Yes | J91: 0 | K91: =IF(OR(G91="",G91=0),"",G91+IF(I91="",0,I91)+IF(J91="",0,J91)) -> 58 | L91: 1 | M91: =IF(OR(K91="",L91=0),"",K91/L91) -> 58 | N91: My Dear Light | O91: Φ56mm matte | P91: Opened, good condition | Q91: Yes | R91: No | S91: No | T91: Yes | V91: MKT-089 | W91: MKT-089.png
A92: 90 | B92: Misa Amane, smiling | C92: Xianyu | D92: 【出死亡笔记弥海砂名古屋快闪吧唧，可直拍】 | E92: https://m.tb.cn/h.87D9x2x | F92: 2026-08-14 | G92: 29 | H92: Yes | J92: 0 | K92: =IF(OR(G92="",G92=0),"",G92+IF(I92="",0,I92)+IF(J92="",0,J92)) -> 29 | L92: 1 | M92: =IF(OR(K92="",L92=0),"",K92/L92) -> 29 | N92: My Dear Light | O92: Φ56mm matte | P92: Opened, good condition | Q92: Yes | R92: No | S92: No | T92: Yes | V92: MKT-090 | W92: MKT-090.png
A93: 91 | B93: Misa Amane, smiling | C93: Xianyu | D93: 【出】dn 名古屋弥海砂吧唧 | E93: https://m.tb.cn/h.8RT87Rt | F93: 2026-08-14 | G93: 35 | H93: No | I93: 6 | J93: 0 | K93: =IF(OR(G93="",G93=0),"",G93+IF(I93="",0,I93)+IF(J93="",0,J93)) -> 41 | L93: 1 | M93: =IF(OR(K93="",L93=0),"",K93/L93) -> 41 | N93: My Dear Light | O93: Φ56mm matte | P93: Opened, good condition | Q93: Yes | R93: No | S93: No | T93: Yes | V93: MKT-091 | W93: MKT-091.png
A94: 92 | B94: Near | C94: Xianyu | D94: 死亡笔记尼亚名古屋快闪吧唧 | E94: https://m.tb.cn/h.8SHTg8I | F94: 2026-08-14 | G94: 28 | H94: Yes | J94: 0 | K94: =IF(OR(G94="",G94=0),"",G94+IF(I94="",0,I94)+IF(J94="",0,J94)) -> 28 | L94: 1 | M94: =IF(OR(K94="",L94=0),"",K94/L94) -> 28 | N94: My Dear Light | O94: Φ56mm matte | P94: Opened, good condition | Q94: Yes | R94: No | S94: No | T94: Yes | V94: MKT-092 | W94: MKT-092.png
A95: 93 | B95: L, dark-gray profile | C95: Xianyu | D95: L 日谷立牌：有原装袋子，75 | E95: https://m.tb.cn/h.8htHALG | F95: 2026-08-14 | G95: 50 | H95: Yes | J95: 0 | K95: =IF(OR(G95="",G95=0),"",G95+IF(I95="",0,I95)+IF(J95="",0,J95)) -> 50 | L95: 1 | M95: =IF(OR(K95="",L95=0),"",K95/L95) -> 50 | N95: My Dear Light | O95: Φ56mm matte | P95: Opened, good condition | Q95: Yes | R95: No | S95: No | T95: Yes | V95: MKT-093 | W95: MKT-093.png
A96: 94 | B96: Misa Amane, choker | C96: Xianyu | D96: 标价包邮出死亡笔记弥海砂-丸井快闪金属吧唧 | E96: https://m.tb.cn/h.87D75Tp | F96: 2026-08-14 | G96: 26 | H96: Yes | I96: 0 | J96: 0 | K96: =IF(OR(G96="",G96=0),"",G96+IF(I96="",0,I96)+IF(J96="",0,J96)) -> 26 | L96: 1 | M96: =IF(OR(K96="",L96=0),"",K96/L96) -> 26 | N96: My Dear Light | O96: Φ56mm matte | P96: Opened, good condition | Q96: Yes | R96: No | S96: No | T96: Yes | V96: MKT-094 | W96: MKT-094.png
A97: 95 | B97: Misa Amane, choker | C97: Xianyu | D97: 死亡笔记deathnote 弥海砂吧唧 密逃原画展 | E97: https://m.tb.cn/h.8RTgf0G | F97: 2026-08-14 | G97: 25 | H97: No | I97: 7 | J97: 0 | K97: =IF(OR(G97="",G97=0),"",G97+IF(I97="",0,I97)+IF(J97="",0,J97)) -> 32 | L97: 1 | M97: =IF(OR(K97="",L97=0),"",K97/L97) -> 32 | N97: My Dear Light | O97: Φ56mm matte | P97: Opened, good condition | Q97: Yes | R97: No | S97: No | T97: Yes | V97: MKT-095 | W97: MKT-095.png
A98: 96 | B98: Misa Amane, choker | C98: Xianyu | D98: 【2个包邮】 | E98: https://m.tb.cn/h.8hGa37b | F98: 2026-08-14 | G98: 20 | H98: Yes | I98: 0 | J98: 0 | K98: =IF(OR(G98="",G98=0),"",G98+IF(I98="",0,I98)+IF(J98="",0,J98)) -> 20 | L98: 1 | M98: =IF(OR(K98="",L98=0),"",K98/L98) -> 20 | N98: My Dear Light | O98: Φ56mm matte | P98: Opened, good condition | Q98: No | R98: No | S98: No | T98: Yes | V98: MKT-096 | W98: MKT-096.png
A99: 97 | B99: L, dark-gray profile | C99: Xianyu | D99: 死亡笔记L原画展个人池30 | E99: https://m.tb.cn/h.87D4z4E | F99: 2026-08-14 | G99: 60 | H99: Yes | J99: 0 | K99: =IF(OR(G99="",G99=0),"",G99+IF(I99="",0,I99)+IF(J99="",0,J99)) -> 60 | L99: 1 | M99: =IF(OR(K99="",L99=0),"",K99/L99) -> 60 | N99: My Dear Light | O99: Φ56mm matte | P99: Opened, good condition | Q99: Yes | R99: No | S99: No | T99: Yes | V99: MKT-097 | W99: MKT-097.png
A100: 98 | B100: Mello | C100: Xianyu | D100: 【国现】死亡笔记抽赏 dn抽赏 梅洛吧唧钥匙扣立牌特典 | E100: https://m.tb.cn/h.8htxwz8 | F100: 2026-08-14 | J100: 0 | K100: =IF(OR(G100="",G100=0),"",G100+IF(I100="",0,I100)+IF(J100="",0,J100)) | L100: 1 | M100: =IF(OR(K100="",L100=0),"",K100/L100) | N100: My Dear Light | O100: Φ56mm matte | P100: Opened, good condition | Q100: No | R100: No | S100: No | T100: Yes | V100: MKT-098 | W100: MKT-098.png
A101: 99 | B101: Misa Amane, choker | C101: Xianyu | D101: 【标价一个，包非偏，可直拍】 | E101: https://m.tb.cn/h.8htBflb | F101: 2026-08-14 | G101: 27.4 | H101: Yes | I101: 0 | J101: 0 | K101: =IF(OR(G101="",G101=0),"",G101+IF(I101="",0,I101)+IF(J101="",0,J101)) -> 27.4 | L101: 1 | M101: =IF(OR(K101="",L101=0),"",K101/L101) -> 27.4 | N101: My Dear Light | O101: Φ56mm matte | P101: Opened, good condition | Q101: No | R101: No | S101: No | T101: Yes | V101: MKT-099 | W101: MKT-099.png
A102: 100 | B102: L, dark-gray profile | C102: Xianyu | D102: 【死亡笔记】 | E102: https://m.tb.cn/h.8htH4tc | F102: 2026-08-14 | G102: 50 | H102: No | I102: 12 | J102: 0 | K102: =IF(OR(G102="",G102=0),"",G102+IF(I102="",0,I102)+IF(J102="",0,J102)) -> 62 | L102: 1 | M102: =IF(OR(K102="",L102=0),"",K102/L102) -> 62 | N102: My Dear Light | O102: Φ56mm matte | P102: Opened, good condition | Q102: No | R102: No | S102: No | T102: Yes | V102: MKT-100 | W102: MKT-100.png
A103: 101 | B103: Light Yagami, profile | C103: Xianyu | D103: 死笔death note新快闪 名古屋大阪丸井原画快闪 | E103: https://m.tb.cn/h.87DYxcs | F103: 2026-08-14 | G103: 65 | H103: Yes | J103: 0 | K103: =IF(OR(G103="",G103=0),"",G103+IF(I103="",0,I103)+IF(J103="",0,J103)) -> 65 | L103: 1 | M103: =IF(OR(K103="",L103=0),"",K103/L103) -> 65 | N103: My Dear Light | O103: Φ56mm matte | P103: Opened, good condition | Q103: No | R103: No | S103: No | T103: Yes | V103: MKT-101 | W103: MKT-101.png
A104: 102 | B104: Light Yagami, profile | C104: Xianyu | D104: 出 死笔death note新快闪 名古屋大阪丸井原画快闪吧 | E104: https://m.tb.cn/h.8SsDS4I | F104: 2026-08-14 | G104: 45 | H104: Yes | J104: 0 | K104: =IF(OR(G104="",G104=0),"",G104+IF(I104="",0,I104)+IF(J104="",0,J104)) -> 45 | L104: 1 | M104: =IF(OR(K104="",L104=0),"",K104/L104) -> 45 | N104: My Dear Light | O104: Φ56mm matte | P104: Opened, good condition | Q104: No | R104: No | S104: No | T104: Yes | V104: MKT-102 | W104: MKT-102.png
A105: 103 | B105: L, light-gray portrait | C105: Xianyu | D105: 【可拆出】Death Note名古屋快闪吧唧 L 夜神月 尼 | E105: https://m.tb.cn/h.8SC1ypy | F105: 2026-08-12 | G105: 50 | H105: Yes | J105: 0 | K105: =IF(OR(G105="",G105=0),"",G105+IF(I105="",0,I105)+IF(J105="",0,J105)) -> 50 | L105: 1 | M105: =IF(OR(K105="",L105=0),"",K105/L105) -> 50 | N105: My Dear Light | O105: Φ56mm matte | P105: Opened, good condition | Q105: No | R105: No | S105: No | T105: Yes | V105: MKT-103 | W105: MKT-103.png
...

Sheet 04_Duplicate_Resale
A1: Duplicate Resale Data
A2: Character Name | B2: Resale Listing Price | C2: Expected Transaction Discount | D2: Expected Transaction Price | E2: Platform Commission Rate | F2: Seller-Paid Shipping | G2: Packaging Material Cost | H2: Net Income per Sale | I2: Expected Sale Probability λ_i | J2: Baseline Net Recovery Value r_i
A3: Required | B3: Conditionally Required | C3: Optional | D3: Auto-calculated | E3: Conditionally Required | F3: Conditionally Required | G3: Optional | H3: Auto-calculated | I3: Optional | J3: Auto-calculated
A4: Light Yagami, front view | B4: 60 | D4: =IF(A4="","",B4*IF(C4="",1,C4)) -> 60 | E4: 0.006 | F4: 6 | G4: 4 | H4: =IF(A4="","",MAX((D4-F4)*(1-E4)-G4,0)) -> 49.676 | I4: 0.6 | J4: =IF(A4="","",H4*IF(I4="",1,I4)) -> 29.8056
A5: Light Yagami, profile | B5: 58 | D5: =IF(A5="","",B5*IF(C5="",1,C5)) -> 58 | E5: 0.006 | F5: 6 | G5: 4 | H5: =IF(A5="","",MAX(D5*(1-E5)-F5-G5,0)) -> 47.652 | I5: 0.6 | J5: =IF(A5="","",H5*IF(I5="",1,I5)) -> 28.5912
A6: L, light-gray portrait | B6: 60 | D6: =IF(A6="","",B6*IF(C6="",1,C6)) -> 60 | E6: 0.006 | F6: 6 | G6: 4 | H6: =IF(A6="","",MAX(D6*(1-E6)-F6-G6,0)) -> 49.64 | I6: 0.6 | J6: =IF(A6="","",H6*IF(I6="",1,I6)) -> 29.784
A7: L, dark-gray profile | B7: 58.5 | D7: =IF(A7="","",B7*IF(C7="",1,C7)) -> 58.5 | E7: 0.006 | F7: 6 | G7: 4 | H7: =IF(A7="","",MAX(D7*(1-E7)-F7-G7,0)) -> 48.149 | I7: 0.6 | J7: =IF(A7="","",H7*IF(I7="",1,I7)) -> 28.8894
A8: Misa Amane, smiling | B8: 37.75 | D8: =IF(A8="","",B8*IF(C8="",1,C8)) -> 37.75 | E8: 0.006 | F8: 6 | G8: 4 | H8: =IF(A8="","",MAX(D8*(1-E8)-F8-G8,0)) -> 27.5235 | I8: 0.6 | J8: =IF(A8="","",H8*IF(I8="",1,I8)) -> 16.5141
A9: Misa Amane, choker | B9: 32 | D9: =IF(A9="","",B9*IF(C9="",1,C9)) -> 32 | E9: 0.006 | F9: 6 | G9: 4 | H9: =IF(A9="","",MAX(D9*(1-E9)-F9-G9,0)) -> 21.808 | I9: 0.6 | J9: =IF(A9="","",H9*IF(I9="",1,I9)) -> 13.0848
A10: Near | B10: 20.33 | D10: =IF(A10="","",B10*IF(C10="",1,C10)) -> 20.33 | E10: 0.006 | F10: 6 | G10: 4 | H10: =IF(A10="","",MAX(D10*(1-E10)-F10-G10,0)) -> 10.20802 | I10: 0.6 | J10: =IF(A10="","",H10*IF(I10="",1,I10)) -> 6.124812
A11: Mello | B11: 40 | D11: =IF(A11="","",B11*IF(C11="",1,C11)) -> 40 | E11: 0.006 | F11: 6 | G11: 4 | H11: =IF(A11="","",MAX(D11*(1-E11)-F11-G11,0)) -> 29.76 | I11: 0.6 | J11: =IF(A11="","",H11*IF(I11="",1,I11)) -> 17.856
D12: =IF(A12="","",B12*IF(C12="",1,C12)) | H12: =IF(A12="","",MAX(D12*(1-E12)-F12-G12,0)) | J12: =IF(A12="","",H12*IF(I12="",1,I12))
D13: =IF(A13="","",B13*IF(C13="",1,C13)) | H13: =IF(A13="","",MAX(D13*(1-E13)-F13-G13,0)) | J13: =IF(A13="","",H13*IF(I13="",1,I13))
D14: =IF(A14="","",B14*IF(C14="",1,C14)) | H14: =IF(A14="","",MAX(D14*(1-E14)-F14-G14,0)) | J14: =IF(A14="","",H14*IF(I14="",1,I14))
D15: =IF(A15="","",B15*IF(C15="",1,C15)) | H15: =IF(A15="","",MAX(D15*(1-E15)-F15-G15,0)) | J15: =IF(A15="","",H15*IF(I15="",1,I15))

Sheet 05_Shipping_Transaction_Rules
A1: Shipping and Transaction Rules
A2: Field Type | B2: Rule Item | C2: Entry
A3: Required | B3: Official Per-Order Shipping | C3: Offline venue 0; online restock not specified
A4: Conditionally Required | B4: Official Bulk-Purchase Shipping | C4: Offline venue 0
A5: Optional | B5: Official Free-Shipping Threshold | C5: No shipping offline; online not specified
A6: Required | B6: Common Buyer Shipping in Secondary Market | C6: Xianyu typically 6–12 CNY or free shipping
A7: Optional | B7: Free-Shipping Ratio in Secondary Records | C7: About 56.9%
A8: Required | B8: Can Missing Characters Be Bought Together? | C8: Yes
A9: Conditionally Required | B9: One-Time Shipping for Combined Purchase
A10: Optional | B10: Buyer Platform Fees | C10: 0
A11: Conditionally Required | B11: Seller Platform Commission Rate | C11: Xianyu about 0.6%–1%;
A12: Conditionally Required | B12: Who Pays Resale Shipping | C12: Seller
A13: Optional | B13: Packaging Material Cost
A14: Required | B14: Baseline Shipping Scenario | C14: Shipping charged per secondary-market order
A15: Optional | B15: Low-Shipping Scenario | C15: All free shipping
A16: Optional | B16: High-Shipping Scenario | C16: Add 12 CNY per character
A17: Required | B17: Transaction Rules Source URL | C17: Xianyu platform rules and sample observation
A18: Required | B18: Transaction Rules Evidence ID

Sheet 06_Data_Quality_Check
A1: Data Quality Checklist
A2: Category | B2: Check Item | C2: Status
A3: Research Object | B3: All records belong to the same series | C3: Pass
A4: Research Object | B4: All records same product type and specs | C4: Pass
A5: Research Object | B5: All records same release batch/version | C5: Pass
A6: Sales Mechanism | B6: Confirmed independent random per pack | C6: Pass
A7: Sales Mechanism | B7: Verified pity, no-duplicate box, and fixed box ratio | C7: Pass
A8: Character Scope | B8: Target character list complete with clear boundaries | C8: Pass
A9: Probability | B9: All target character probabilities are positive | C9: Pass
A10: Probability | B10: Sum of baseline probabilities equals 1 | C10: Pass
A11: Probability | B11: Equal-probability basis stated when no official probs | C11: Pass
A12: Sampling | B12: Same sampling time window for all characters | C12: Pass
A13: Sampling | B13: Same sampling rules for all characters | C13: Pass
... A30: Submission | B30: File naming and folder structure meet requirements | C30: Pass

Sheet 07_Collection_Progress_Summary
A1: Secondary-Market Data Collection Progress by Character
A2: Character ID | B2: Character Name | C2: Raw Record Count | D2: Valid Record Count | E2: Valid Records Missing Evidence | F2: Sample Assessment
A3: =IF('02_Character_Probabilities'!B3="","",'02_Character_Probabilities'!A3) -> 1 | B3: =IF('02_Character_Probabilities'!B3="","",'02_Character_Probabilities'!B3) -> Light Yagami, front view | C3: =IF(B3="","",COUNTIF('03_Secondary_Market_Raw_Data'!B$3:B$299,B3)) -> 18 | D3: =IF(B3="","",COUNTIFS('03_Secondary_Market_Raw_Data'!B$3:B$299,B3,'03_Secondary_Market_Raw_Data'!T$3:T$299,"Yes")) -> 16 | E3: =IF(B3="","",COUNTIFS('03_Secondary_Market_Raw_Data'!B$3:B$299,B3,'03_Secondary_Market_Raw_Data'!T$3:T$299,"Yes",'03_Secondary_Market_Raw_Data'!V$3:V$299,"")) -> 0 | F3: =IF(B3="","Not started",IF(D3>=15,"Satisfactory",IF(D3>=8,"Basically usable",IF(D3>=5,"Weak",IF(D3>0,"Insufficient","Not started"))))) -> Satisfactory
A4: =IF('02_Character_Probabilities'!B4="","",'02_Character_Probabilities'!A4) -> 2 | B4: =IF('02_Character_Probabilities'!B4="","",'02_Character_Probabilities'!B4) -> Light Yagami, profile | C4: =IF(B4="","",COUNTIF('03_Secondary_Market_Raw_Data'!B$3:B$299,B4)) -> 17 | D4: =IF(B4="","",COUNTIFS('03_Secondary_Market_Raw_Data'!B$3:B$299,B4,'03_Secondary_Market_Raw_Data'!T$3:T$299,"Yes")) -> 17 | E4: =IF(B4="","",COUNTIFS('03_Secondary_Market_Raw_Data'!B$3:B$299,B4,'03_Secondary_Market_Raw_Data'!T$3:T$299,"Yes",'03_Secondary_Market_Raw_Data'!V$3:V$299,"")) -> 0 | F4: =IF(B4="","Not started",IF(D4>=15,"Satisfactory",IF(D4>=8,"Basically usable",IF(D4>=5,"Weak",IF(D4>0,"Insufficient","Not started"))))) -> Satisfactory
A5: =IF('02_Character_Probabilities'!B5="","",'02_Character_Probabilities'!A5) -> 3 | B5: =IF('02_Character_Probabilities'!B5="","",'02_Character_Probabilities'!B5) -> L, light-gray portrait | C5: =IF(B5="","",COUNTIF('03_Secondary_Market_Raw_Data'!B$3:B$299,B5)) -> 20 | D5: =IF(B5="","",COUNTIFS('03_Secondary_Market_Raw_Data'!B$3:B$299,B5,'03_Secondary_Market_Raw_Data'!T$3:T$299,"Yes")) -> 20 | E5: =IF(B5="","",COUNTIFS('03_Secondary_Market_Raw_Data'!B$3:B$299,B5,'03_Secondary_Market_Raw_Data'!T$3:T$299,"Yes",'03_Secondary_Market_Raw_Data'!V$3:V$299,"")) -> 0 | F5: =IF(B5="","Not started",IF(D5>=15,"Satisfactory",IF(D5>=8,"Basically usable",IF(D5>=5,"Weak",IF(D5>0,"Insufficient","Not started"))))) -> Satisfactory
A6: =IF('02_Character_Probabilities'!B6="","",'02_Character_Probabilities'!A6) -> 4 | B6: =IF('02_Character_Probabilities'!B6="","",'02_Character_Probabilities'!B6) -> L, dark-gray profile | C6: =IF(B6="","",COUNTIF('03_Secondary_Market_Raw_Data'!B$3:B$299,B6)) -> 14 | D6: =IF(B6="","",COUNTIFS('03_Secondary_Market_Raw_Data'!B$3:B$299,B6,'03_Secondary_Market_Raw_Data'!T$3:T$299,"Yes")) -> 14 | E6: =IF(B6="","",COUNTIFS('03_Secondary_Market_Raw_Data'!B$3:B$299,B6,'03_Secondary_Market_Raw_Data'!T$3:T$299,"Yes",'03_Secondary_Market_Raw_Data'!V$3:V$299,"")) -> 0 | F6: =IF(B6="","Not started",IF(D6>=15,"Satisfactory",IF(D6>=8,"Basically usable",IF(D6>=5,"Weak",IF(D6>0,"Insufficient","Not started"))))) -> Basically usable
A7: =IF('02_Character_Probabilities'!B7="","",'02_Character_Probabilities'!A7) -> 5 | B7: =IF('02_Character_Probabilities'!B7="","",'02_Character_Probabilities'!B7) -> Misa Amane, smiling | C7: =IF(B7="","",COUNTIF('03_Secondary_Market_Raw_Data'!B$3:B$299,B7)) -> 16 | D7: =IF(B7="","",COUNTIFS('03_Secondary_Market_Raw_Data'!B$3:B$299,B7,'03_Secondary_Market_Raw_Data'!T$3:T$299,"Yes")) -> 14 | E7: =IF(B7="","",COUNTIFS('03_Secondary_Market_Raw_Data'!B$3:B$299,B7,'03_Secondary_Market_Raw_Data'!T$3:T$299,"Yes",'03_Secondary_Market_Raw_Data'!V$3:V$299,"")) -> 0 | F7: =IF(B7="","Not started",IF(D7>=15,"Satisfactory",IF(D7>=8,"Basically usable",IF(D7>=5,"Weak",IF(D7>0,"Insufficient","Not started"))))) -> Basically usable
A8: =IF('02_Character_Probabilities'!B8="","",'02_Character_Probabilities'!A8) -> 6 | B8: =IF('02_Character_Probabilities'!B8="","",'02_Character_Probabilities'!B8) -> Misa Amane, choker | C8: =IF(B8="","",COUNTIF('03_Secondary_Market_Raw_Data'!B$3:B$299,B8)) -> 15 | D8: =IF(B8="","",COUNTIFS('03_Secondary_Market_Raw_Data'!B$3:B$299,B8,'03_Secondary_Market_Raw_Data'!T$3:T$299,"Yes")) -> 15 | E8: =IF(B8="","",COUNTIFS('03_Secondary_Market_Raw_Data'!B$3:B$299,B8,'03_Secondary_Market_Raw_Data'!T$3:T$299,"Yes",'03_Secondary_Market_Raw_Data'!V$3:V$299,"")) -> 0 | F8: =IF(B8="","Not started",IF(D8>=15,"Satisfactory",IF(D8>=8,"Basically usable",IF(D8>=5,"Weak",IF(D8>0,"Insufficient","Not started"))))) -> Satisfactory
A9: =IF('02_Character_Probabilities'!B9="","",'02_Character_Probabilities'!A9) -> 7 | B9: =IF('02_Character_Probabilities'!B9="","",'02_Character_Probabilities'!B9) -> Near | C9: =IF(B9="","",COUNTIF('03_Secondary_Market_Raw_Data'!B$3:B$299,B9)) -> 18 | D9: =IF(B9="","",COUNTIFS('03_Secondary_Market_Raw_Data'!B$3:B$299,B9,'03_Secondary_Market_Raw_Data'!T$3:T$299,"Yes")) -> 17 | E9: =IF(B9="","",COUNTIFS('03_Secondary_Market_Raw_Data'!B$3:B$299,B9,'03_Secondary_Market_Raw_Data'!T$3:T$299,"Yes",'03_Secondary_Market_Raw_Data'!V$3:V$299,"")) -> 0 | F9: =IF(B9="","Not started",IF(D9>=15,"Satisfactory",IF(D9>=8,"Basically usable",IF(D9>=5,"Weak",IF(D9>0,"Insufficient","Not started"))))) -> Satisfactory
A10: =IF('02_Character_Probabilities'!B10="","",'02_Character_Probabilities'!A10) -> 8 | B10: =IF('02_Character_Probabilities'!B10="","",'02_Character_Probabilities'!B10) -> Mello | C10: =IF(B10="","",COUNTIF('03_Secondary_Market_Raw_Data'!B$3:B$299,B10)) -> 16 | D10: =IF(B10="","",COUNTIFS('03_Secondary_Market_Raw_Data'!B$3:B$299,B10,'03_Secondary_Market_Raw_Data'!T$3:T$299,"Yes")) -> 14 | E10: =IF(B10="","",COUNTIFS('03_Secondary_Market_Raw_Data'!B$3:B$299,B10,'03_Secondary_Market_Raw_Data'!T$3:T$299,"Yes",'03_Secondary_Market_Raw_Data'!V$3:V$299,"")) -> 0 | F10: =IF(B10="","Not started",IF(D10>=15,"Satisfactory",IF(D10>=8,"Basically usable",IF(D10>=5,"Weak",IF(D10>0,"Insufficient","Not started"))))) -> Basically usable
A11: =IF('02_Character_Probabilities'!#REF!="","",'02_Character_Probabilities'!#REF!) -> #REF! | B11: =IF('02_Character_Probabilities'!#REF!="","",'02_Character_Probabilities'!#REF!) -> #REF! | C11: =IF(B11="","",COUNTIF('03_Secondary_Market_Raw_Data'!B$3:B$299,B11)) -> #REF! | D11: =IF(B11="","",COUNTIFS('03_Secondary_Market_Raw_Data'!B$3:B$299,B11,'03_Secondary_Market_Raw_Data'!T$3:T$299,"Yes")) -> #REF! | E11: =IF(B11="","",COUNTIFS('03_Secondary_Market_Raw_Data'!B$3:B$299,B11,'03_Secondary_Market_Raw_Data'!T$3:T$299,"Yes",'03_Secondary_Market_Raw_Data'!V$3:V$299,"")) -> #REF! | F11: =IF(B11="","Not started",IF(D11>=15,"Satisfactory",IF(D11>=8,"Basically usable",IF(D11>=5,"Weak",IF(D11>0,"Insufficient","Not started"))))) -> #REF!
A12: =IF('02_Character_Probabilities'!#REF!="","",'02_Character_Probabilities'!#REF!) -> #REF! | B12: =IF('02_Character_Probabilities'!#REF!="","",'02_Character_Probabilities'!#REF!) -> #REF! | C12: =IF(B12="","",COUNTIF('03_Secondary_Market_Raw_Data'!B$3:B$299,B12)) -> #REF! | D12: =IF(B12="","",COUNTIFS('03_Secondary_Market_Raw_Data'!B$3:B$299,B12,'03_Secondary_Market_Raw_Data'!T$3:T$299,"Yes")) -> #REF! | E12: =IF(B12="","",COUNTIFS('03_Secondary_Market_Raw_Data'!B$3:B$299,B12,'03_Secondary_Market_Raw_Data'!T$3:T$299,"Yes",'03_Secondary_Market_Raw_Data'!V$3:V$299,"")) -> #REF! | F12: =IF(B12="","Not started",IF(D12>=15,"Satisfactory",IF(D12>=8,"Basically usable",IF(D12>=5,"Weak",IF(D12>0,"Insufficient","Not started"))))) -> #REF!
A13: =IF('02_Character_Probabilities'!#REF!="","",'02_Character_Probabilities'!#REF!) -> #REF! | B13: =IF('02_Character_Probabilities'!#REF!="","",'02_Character_Probabilities'!#REF!) -> #REF! | C13: =IF(B13="","",COUNTIF('03_Secondary_Market_Raw_Data'!B$3:B$299,B13)) -> #REF! | D13: =IF(B13="","",COUNTIFS('03_Secondary_Market_Raw_Data'!B$3:B$299,B13,'03_Secondary_Market_Raw_Data'!T$3:T$299,"Yes")) -> #REF! | E13: =IF(B13="","",COUNTIFS('03_Secondary_Market_Raw_Data'!B$3:B$299,B13,'03_Secondary_Market_Raw_Data'!T$3:T$299,"Yes",'03_Secondary_Market_Raw_Data'!V$3:V$299,"")) -> #REF! | F13: =IF(B13="","Not started",IF(D13>=15,"Satisfactory",IF(D13>=8,"Basically usable",IF(D13>=5,"Weak",IF(D13>0,"Insufficient","Not started"))))) -> #REF!
A14: =IF('02_Character_Probabilities'!#REF!="","",'02_Character_Probabilities'!#REF!) -> #REF! | B14: =IF('02_Character_Probabilities'!#REF!="","",'02_Character_Probabilities'!#REF!) -> #REF! | C14: =IF(B14="","",COUNTIF('03_Secondary_Market_Raw_Data'!B$3:B$299,B14)) -> #REF! | D14: =IF(B14="","",COUNTIFS('03_Secondary_Market_Raw_Data'!B$3:B$299,B14,'03_Secondary_Market_Raw_Data'!T$3:T$299,"Yes")) -> #REF! | E14: =IF(B14="","",COUNTIFS('03_Secondary_Market_Raw_Data'!B$3:B$299,B14,'03_Secondary_Market_Raw_Data'!T$3:T$299,"Yes",'03_Secondary_Market_Raw_Data'!V$3:V$299,"")) -> #REF! | F14: =IF(B14="","Not started",IF(D14>=15,"Satisfactory",IF(D14>=8,"Basically usable",IF(D14>=5,"Weak",IF(D14>0,"Insufficient","Not started"))))) -> #REF!

Sheet 08_Data_Dictionary
A1: Data Dictionary: Field Definitions, Formats, and Examples
A2: Worksheet | B2: Field Name | C2: Field Type | D2: Definition | E2: Entry Format | F2: Allowed Values / Rules
A3: 01_Series_Basic_Info | B3: Full Series Name | C3: Required | D3: Use the full name from the official page | E3: Text / numeric / date | F3: Fill as instructed
A4: 01_Series_Basic_Info | B4: Work / Title Name | C4: Required | D4: Related anime, game, or film/TV work | E4: Text / numeric / date | F4: Fill as instructed
A5: 01_Series_Basic_Info | B5: Product Type | C5: Required | D5: Badge, card, standee, etc. | E5: Text / numeric / date | F5: Fill as instructed
A6: 01_Series_Basic_Info | B6: Product Specs / Size | C6: Required | D6: Ensure consistent specs for later price records | E6: Text / numeric / date | F6: Fill as instructed
A7: 01_Series_Basic_Info | B7: Release Batch / Version | C7: Required | D7: First edition, reprint, Vol.1, etc. | E7: Text / numeric / date | F7: Fill as instructed
A8: 01_Series_Basic_Info | B8: Official Release Date | C8: Optional | D8: Enter as YYYY-MM-DD | E8: Text / numeric / date | F8: Fill as instructed
A9: 01_Series_Basic_Info | B9: Total Number of Target Characters n | C9: Required | D9: Recommended 6–12; exclude explicitly out-of-scope designs | E9: Text / numeric / date | F9: Fill as instructed
A10: 01_Series_Basic_Info | B10: Official Random Unit Price | C10: Required | D10: Product price only; exclude shipping | E10: Text / numeric / date | F10: Fill as instructed
A11: 01_Series_Basic_Info | B11: Official Purchase Channels | C11: Required | D11: Official site, official store, or other formal channels | E11: Text / numeric / date | F11: Fill as instructed
A12: 01_Series_Basic_Info | B12: Official Shipping Rules | C12: Required | D12: State per-order shipping, combined shipping, or free-shipping rules | E12: Text / numeric / date | F12: Fill as instructed
A13: 01_Series_Basic_Info | B13: Other Official Fees | C13: Optional | D13: Enter 0 if none | E13: Text / numeric / date | F13: Fill as instructed
... A77: 05_Shipping_Transaction_Rules | B77: Transaction Rules Evidence ID | C77: Required | D77: Corresponding screenshot | E77: Text/Numeric | F77: Fill as instructed
